main.py
mseep_arduino_mcp-0.1.1.dist-info/METADATA
mseep_arduino_mcp-0.1.1.dist-info/WHEEL
mseep_arduino_mcp-0.1.1.dist-info/entry_points.txt
mseep_arduino_mcp-0.1.1.dist-info/top_level.txt
mseep_arduino_mcp-0.1.1.dist-info/RECORD
