Metadata-Version: 2.4
Name: mseep-arduino-mcp
Version: 0.1.1
Summary: This is an Arduino MCP server
Author-email: mseep <support@skydeck.ai>
Requires-Python: >=3.12
Requires-Dist: asyncio>=3.4.3
Requires-Dist: fastmcp>=2.8.1
Requires-Dist: pyfirmata2>=2.5.1
